__init__.py
main.py
todos.py
cli_todo_manager-0.1.1.dist-info/METADATA
cli_todo_manager-0.1.1.dist-info/WHEEL
cli_todo_manager-0.1.1.dist-info/entry_points.txt
cli_todo_manager-0.1.1.dist-info/top_level.txt
cli_todo_manager-0.1.1.dist-info/RECORD
