Metadata-Version: 2.1
Name: cli-todo-manager
Version: 0.1.1
Summary: A simple command line utility that manages your ToDos
Home-page: https://github.com/timnw2000/todos
Author: Tim Nwungang
Author-email: timnw.dev@gmail.com
Maintainer-email: timnw.dev@gmail.com
License: MIT
Project-URL: Documentation, https://github.com/timnw2000/todos/blob/main/README.md
Requires: setuptools
Requires-Dist: prettytable ==3.9.0
Requires-Dist: tabulate ==0.9.0
Requires-Dist: wcwidth ==0.2.12
